cross_sysroot/__init__.py
cross_sysroot/cross_gcc.py
cross_sysroot/cross_sysroot.py
cross_sysroot/fixup_sysroot.py
cross_sysroot/package_database.py
cross_sysroot-0.4.dist-info/LICENSE
cross_sysroot-0.4.dist-info/METADATA
cross_sysroot-0.4.dist-info/WHEEL
cross_sysroot-0.4.dist-info/entry_points.txt
cross_sysroot-0.4.dist-info/top_level.txt
cross_sysroot-0.4.dist-info/RECORD
