Metadata-Version: 2.1
Name: cross-sysroot
Version: 0.4
Summary: Utility to generate a sysroot tree from a Linux distribution
Home-page: https://github.com/labapart/cross_sysroot
Author: Olivier Martin
Author-email: olivier@labapart.com
License: UNKNOWN
Platform: UNKNOWN
License-File: LICENSE
Requires-Dist: setuptools
Requires-Dist: pysqlite3
